caiche/__init__.py
caiche/core.py
caiche/enums.py
llm_caiche-0.1.2.dist-info/LICENSE
llm_caiche-0.1.2.dist-info/METADATA
llm_caiche-0.1.2.dist-info/WHEEL
llm_caiche-0.1.2.dist-info/top_level.txt
llm_caiche-0.1.2.dist-info/RECORD
