Metadata-Version: 2.1
Name: llm-caiche
Version: 0.1.2
Summary: Unified Language Model Cache.
Home-page: https://github.com/structuraize/caiche
Author: Structuraize
Author-email: info@structuraize.com
Classifier: Programming Language :: Python :: 3
Classifier: Programming Language :: Python :: 3.7
Classifier: Programming Language :: Python :: 3.8
Classifier: Programming Language :: Python :: 3.9
Classifier: Programming Language :: Python :: 3.10
Classifier: Programming Language :: Python :: 3.11
Classifier: License :: OSI Approved :: MIT License
Classifier: Operating System :: OS Independent
Requires-Python: >=3.7
License-File: LICENSE
Requires-Dist: requests >=2.20.0
